[
  {
    "id": 1,
    "productos": [
      {
        "id": 11,
        "producto": {
          "title": "iPhone",
          "price": "300",
          "url": "https://www.apple.com/newsroom/images/product/iphone/geo/apple_iphone-12_new-design_geo_10132020_big.jpg.large_2x.jpg"
        }
      },
      {
        "id": 12,
        "producto": {
          "title": "Prueba",
          "price": "1000",
          "url": "https://www.apple.com/newsroom/images/product/iphone/geo/apple_iphone-12_new-design_geo_10132020_big.jpg.large_2x.jpg"
        }
      }
    ]
  },
  {
    "id": 0,
    "productos": [
      {

          "id": 2,
          "producto": {
            "title": "Naranja",
            "price": 60,
            "url": "https://upload.wikimedia.org/wikipedia/commons/thumb/c/c8/Orange_logo.svg/1200px-Orange_logo.svg.png"
          }
        },
        {
          "id": 3,
          "producto": {
            "title": "Enano",
            "price": "10000000",
            "url": "https://i.imgur.com/5bC63Yh.gif"
          }
        },
        {
          "id": 9,
          "producto": {
            "title": "Apple",
            "price": "40",
            "url": "https://i.imgur.com/X99fUfw.jpg"
          }
        }
    ]
  }
]
